asi1_mcp_cli/__init__.py
asi1_mcp_cli/agent_chat.py
asi1_mcp_cli/cli.py
asi1_mcp_cli/config.py
asi1_mcp_cli/const.py
asi1_mcp_cli/input.py
asi1_mcp_cli/memory.py
asi1_mcp_cli/output.py
asi1_mcp_cli/prompt.py
asi1_mcp_cli/storage.py
asi1_mcp_cli/tool.py
asi1_mcp_cli-0.1.7.dist-info/METADATA
asi1_mcp_cli-0.1.7.dist-info/WHEEL
asi1_mcp_cli-0.1.7.dist-info/entry_points.txt
asi1_mcp_cli-0.1.7.dist-info/licenses/LICENSE
asi1_mcp_cli-0.1.7.dist-info/RECORD
