Metadata-Version: 2.4
Name: asi1-mcp-cli
Version: 0.1.7
Summary: A powerful CLI for interacting with the ASI:One LLM and Model Context Protocol (MCP) servers
Author-email: Fetch Team <gautam.kumar@fetch.ai>
Maintainer-email: Fetch Team <gautam.kumar@fetch.ai>
License-File: LICENSE
Keywords: ai,asi1,chatbot,cli,langchain,mcp
Classifier: Development Status :: 4 - Beta
Classifier: Intended Audience :: Developers
Classifier: License :: OSI Approved :: MIT License
Classifier: Operating System :: OS Independent
Classifier: Programming Language :: Python :: 3
Classifier: Programming Language :: Python :: 3.8
Classifier: Programming Language :: Python :: 3.9
Classifier: Programming Language :: Python :: 3.10
Classifier: Programming Language :: Python :: 3.11
Classifier: Programming Language :: Python :: 3.12
Classifier: Topic :: Internet :: WWW/HTTP :: Dynamic Content
Classifier: Topic :: Scientific/Engineering :: Artificial Intelligence
Classifier: Topic :: Software Development :: Libraries :: Python Modules
Requires-Python: >=3.8
Requires-Dist: aiosqlite>=0.17.0
Requires-Dist: anyio>=3.6.2
Requires-Dist: click>=8.0.0
Requires-Dist: commentjson>=0.9.0
Requires-Dist: filetype>=1.2.0
Requires-Dist: jsonschema-pydantic>=0.2.0
Requires-Dist: langchain-openai>=0.1.0
Requires-Dist: langchain>=0.1.0
Requires-Dist: langgraph>=0.0.26
Requires-Dist: mcp>=0.1.0
Requires-Dist: numpy
Requires-Dist: pydantic-settings>=2.0.0
Requires-Dist: pydantic>=2.0.0
Requires-Dist: python-dotenv>=1.0.0
Requires-Dist: rich>=12.0.0
Requires-Dist: uagents-core>=0.3.4
Requires-Dist: uagents>=0.9.0
Requires-Dist: yaspin
